server.py
mseep_mapas_mentais-0.1.2.dist-info/licenses/LICENSE
mseep_mapas_mentais-0.1.2.dist-info/METADATA
mseep_mapas_mentais-0.1.2.dist-info/WHEEL
mseep_mapas_mentais-0.1.2.dist-info/entry_points.txt
mseep_mapas_mentais-0.1.2.dist-info/top_level.txt
mseep_mapas_mentais-0.1.2.dist-info/RECORD
