Metadata-Version: 2.4
Name: mseep-mapas-mentais
Version: 0.1.2
Summary: Add your description here
Author-email: mseep <support@skydeck.ai>
Requires-Python: >=3.13
License-File: LICENSE
Requires-Dist: mcp[cli]>=1.6.0
Dynamic: license-file
